{
  "name": "Caleb Hiemstra",
  "headerTaglineOne": "Hello 👋",
  "headerTaglineTwo": "I'm Caleb Hiemstra - Computer Systems Technician",
  "headerTaglineThree": "and IT enthusiast",
  "headerTaglineFour": "based in Kitchener, ON.",
  "showCursor": true,
  "showBlog": false,
  "darkMode": true,
  "showResume": true,
  "socials": [
    {
      "id": "1",
      "title": "LinkedIn",
      "link": "https://www.linkedin.com/in/caleb-hiemstra/"
    },
    {
      "id": "2",
      "title": "Email",
      "link": "mailto:chiemstra3609@conestogac.on.ca"
    }
  ],
  "projects": [],
  "services": [],
  "aboutpara": "Computer Systems Technician graduate (August 2024) seeking to build on school and work knowledge by obtaining a full-time position in the IT industry.",
  "resume": {
    "tagline": "👋 I'm a Computer Systems Technician.",
    "description": "Experienced in IT support, troubleshooting, network design, and development with C and Python. Passionate about all things computers.",
    "experiences": [
      {
        "id": "1",
        "dates": "January 2024 - April 2024",
        "type": "Co-op",
        "position": "IT Helpdesk",
        "company": "VLInteractive, Guelph, ON",
        "bullets": [
          "Responded to customer and employee IT tickets.",
          "Setup and troubleshot customer and employee computers.",
          "Installed software and maintained hardware.",
          "Helped with IT team's long-term projects.",
          "Gained knowledge of Windows administration tools.",
          "Communicated effectively with co-workers and customers."
        ]
      },
      {
        "id": "2",
        "dates": "May 2022 - August 2022",
        "type": "Co-op",
        "position": "IT Helpdesk",
        "company": "VLInteractive, Guelph, ON",
        "bullets": [
          "Responded to customer and employee IT tickets.",
          "Setup and troubleshot customer and employee computers.",
          "Installed software and maintained hardware.",
          "Helped with IT team's long-term projects.",
          "Gained knowledge of Windows administration tools.",
          "Communicated effectively with co-workers and customers."
        ]
      },
      {
        "id": "3",
        "dates": "May 2021 - August 2021",
        "type": "Full Time",
        "position": "Furniture Assembly",
        "company": "Hauser Industries Inc, Waterloo, ON",
        "bullets": [
          "Assembled high-end patio furniture meeting precise standards.",
          "Used a wide variety of tools to complete furniture assembly.",
          "Worked to tight deadlines.",
          "Collaborated with team members to complete large projects.",
          "Utilized barcode scanners to organize workflow."
        ]
      },
      {
        "id": "4",
        "dates": "Nov 2017 - Sept 2019",
        "type": "Part Time",
        "position": "Kitchen Assistant",
        "company": "Fork and Cork Grill, Kitchener, ON",
        "bullets": [
          "Worked in a fast-paced kitchen environment.",
          "Washed dishes and prepped food.",
          "Supported other restaurant staff in daily operations."
        ]
      }
    ],
    "education": {
      "universityName": "Conestoga College, Waterloo, Ontario",
      "universityDate": "January 2023 – Present",
      "universityPara": "Program focuses on installing, configuring, and troubleshooting workstations and server computers, networks, and virtual infrastructure. Practical work is completed on industry-standard hardware and software encountered in the workplace."
    },
    "previousEducation": [
      {
        "universityName": "Conestoga College, Cambridge, Ontario",
        "universityDate": "Sep 2020 – Aug 2022",
        "universityPara": "Completed courses in Digital and Analog Electronics, Embedded Systems, Software, Signal Processing, Communication Systems, Math, and Physics. Project-based learning with hands-on skill development and exposure to engineering environments and processes."
      },
      {
        "universityName": "Woodland Christian High School, Breslau, Ontario",
        "universityDate": "Sep 2016 – June 2020",
        "universityPara": "Graduated as an Ontario Scholar."
      }
    ],
    "languages": [
      "C",
      "Python",
      "Javascript",
      "HTML5",
      "CSS"
    ],
    "frameworks": [],
    "others": [
      "Microsoft 365",
      "Windows Administration",
      "Network Design"
    ]
  },
  "extracurriculars": {
    "activities": [
      {
        "title": "First Robotics competitions",
        "description": "Participated as a scout, collecting and collating data on other teams. Helped the team make it to the World Championship from 2017-2019."
      }
    ]
  },
  "interests": [
    "Building computers - built first computer in 2017",
    "Cyber security"
  ]
}
